totokenizers/__init__.py
totokenizers/errors.py
totokenizers/factories.py
totokenizers/jsonschema_formatter.py
totokenizers/model_info.py
totokenizers/openai.py
totokenizers/openai_info.py
totokenizers/protocols.py
totokenizers/schemas.py
totokenizers/anthropic/__init__.py
totokenizers/anthropic/anthropic.py
totokenizers/anthropic/info.py
totokenizers/anthropic/tokenizer.json
totokenizers/google/__init__.py
totokenizers/google/google.py
totokenizers/mockai/__init__.py
totokenizers/mockai/info.py
totokenizers/mockai/tokenizer.py
totokenizers-1.8.0.dist-info/METADATA
totokenizers-1.8.0.dist-info/WHEEL
totokenizers-1.8.0.dist-info/top_level.txt
totokenizers-1.8.0.dist-info/zip-safe
totokenizers-1.8.0.dist-info/RECORD
