Metadata-Version: 2.4
Name: totokenizers
Version: 1.8.0
Summary: Text tokenizers.
Home-page: https://github.com/TeiaLabs/totokenizers
Author: TeiaLabs
Author-email: contato@teialabs.com
Requires-Python: >=3.11
Requires-Dist: google-cloud-aiplatform
Requires-Dist: tiktoken
Requires-Dist: tokenizers<0.22,>=0.21
Provides-Extra: test
Requires-Dist: pytest; extra == "test"
Dynamic: author
Dynamic: author-email
Dynamic: description
Dynamic: description-content-type
Dynamic: home-page
Dynamic: provides-extra
Dynamic: requires-dist
Dynamic: requires-python
Dynamic: summary
